mpl_image_segmenter/__init__.py
mpl_image_segmenter/_segmenter.py
mpl_image_segmenter/py.typed
mpl_image_segmenter/example_images/__init__.py
mpl_image_segmenter/example_images/example_img_stack.npz
mpl_image_segmenter/example_images/mask.npz
mpl_image_segmenter-0.2.1.dist-info/METADATA
mpl_image_segmenter-0.2.1.dist-info/WHEEL
mpl_image_segmenter-0.2.1.dist-info/licenses/LICENSE
mpl_image_segmenter-0.2.1.dist-info/RECORD
