Metadata-Version: 2.4
Name: mpl-image-segmenter
Version: 0.2.1
Summary: Manually segment images with matplotlib
Project-URL: homepage, https://github.com/ianhi/mpl-image-segmenter
Project-URL: repository, https://github.com/ianhi/mpl-image-segmenter
Author: Ian Hunt-Isaak
Author-email: ianhuntisaak@gmail.com
License: BSD 3-Clause License
License-File: LICENSE
Classifier: Development Status :: 3 - Alpha
Classifier: License :: OSI Approved :: BSD License
Classifier: Programming Language :: Python :: 3
Classifier: Programming Language :: Python :: 3.8
Classifier: Programming Language :: Python :: 3.9
Classifier: Programming Language :: Python :: 3.10
Requires-Python: >=3.8
Requires-Dist: matplotlib>=3.5
Requires-Dist: mpl-pan-zoom
Requires-Dist: numpy
Provides-Extra: dev
Requires-Dist: black; extra == 'dev'
Requires-Dist: ipython; extra == 'dev'
Requires-Dist: mypy; extra == 'dev'
Requires-Dist: pdbpp; extra == 'dev'
Requires-Dist: pre-commit; extra == 'dev'
Requires-Dist: pytest; extra == 'dev'
Requires-Dist: pytest-cov; extra == 'dev'
Requires-Dist: rich; extra == 'dev'
Requires-Dist: ruff; extra == 'dev'
Provides-Extra: doc
Requires-Dist: autoapi; extra == 'doc'
Requires-Dist: furo; extra == 'doc'
Requires-Dist: ipympl; extra == 'doc'
Requires-Dist: myst-nb; extra == 'doc'
Requires-Dist: numpydoc; extra == 'doc'
Requires-Dist: sphinx; extra == 'doc'
Requires-Dist: sphinx-autobuild; extra == 'doc'
Requires-Dist: sphinx-copybutton; extra == 'doc'
Provides-Extra: test
Requires-Dist: pytest-cov; extra == 'test'
Requires-Dist: pytest>=6.0; extra == 'test'
